<?xml version="1.0" encoding="UTF-8"?>
<con:soapui-project id="86f06c07-c8c5-4ac0-8acc-206d18bfc092" activeEnvironment="Default" name="Tomee Hello World" soapui-version="5.5.0" xmlns:con="http://eviware.com/soapui/config"><con:settings/><con:interface xsi:type="con:RestService" id="48a2c1eb-a16d-4c2a-86fd-01132fceaf50" wadlVersion="http://wadl.dev.java.net/2009/02" name="http://localhost:8080" type="rest" xmlns:xsi="http://www.w3.org/2001/XMLSchema-instance"><con:settings/><con:definitionCache/><con:endpoints><con:endpoint>http://localhost:8080</con:endpoint></con:endpoints><con:resource name="HelloWorld" path="/tomee-hello-world-1.0/helloWorld" id="54f61a31-e5dc-4af1-986e-e5024e76727a"><con:settings/><con:parameters/><con:resource name="witArgument" path="withArgument" id="9d62e02c-cb03-497d-891e-e81704fe8c3b"><con:settings/><con:parameters><con:parameter><con:name>argument</con:name><con:value/><con:style>QUERY</con:style><con:default/><con:description xsi:nil="true"/></con:parameter></con:parameters><con:method name="Method 1" id="07df5bcb-9da0-43c9-bf2d-45df9e407459" method="GET"><con:settings/><con:parameters/><con:representation type="FAULT"><con:mediaType xsi:nil="true"/><con:status>404</con:status><con:params/><con:element>data</con:element></con:representation><con:representation type="RESPONSE"><con:mediaType>text/plain</con:mediaType><con:status>200</con:status><con:params/><con:element>data</con:element></con:representation><con:request name="Request 1" id="c45f660c-f81e-4ccc-9c69-4540ecafb20e" mediaType="application/json"><con:settings><con:setting id="com.eviware.soapui.impl.wsdl.WsdlRequest@request-headers">&lt;xml-fragment/></con:setting></con:settings><con:endpoint>http://localhost:8080</con:endpoint><con:request/><con:originalUri>http://localhost/tomee-hello-world-1.0/helloWorld/witArgument</con:originalUri><con:credentials><con:authType>No Authorization</con:authType></con:credentials><con:jmsConfig JMSDeliveryMode="PERSISTENT"/><con:jmsPropertyConfig/><con:parameters><entry key="argument" value="test" xmlns="http://eviware.com/soapui/config"/></con:parameters><con:parameterOrder><con:entry>argument</con:entry></con:parameterOrder></con:request></con:method></con:resource><con:resource name="withArgument" path="withArgument" id="b203dc28-eeb3-4cbf-bd11-3640a7f08244"><con:settings/><con:parameters/><con:method name="Method 1" id="c52ffddc-c303-4609-b8ca-606d3ff3211b" method="POST"><con:settings/><con:parameters/><con:representation type="FAULT"><con:mediaType xsi:nil="true"/><con:status>415</con:status><con:params/><con:element>data</con:element></con:representation><con:representation type="REQUEST"><con:mediaType>application/json</con:mediaType><con:params/></con:representation><con:representation type="FAULT"><con:mediaType xsi:nil="true"/><con:status>415</con:status><con:params/><con:element>data</con:element></con:representation><con:representation type="RESPONSE"><con:mediaType>text/plain</con:mediaType><con:status>200</con:status><con:params/><con:element>data</con:element></con:representation><con:representation type="REQUEST"><con:mediaType>text/plain</con:mediaType><con:params/></con:representation><con:request name="Request 1" id="7e3984ac-f442-4f15-ace4-e29e17d046e2" mediaType="text/plain" postQueryString="false"><con:settings><con:setting id="com.eviware.soapui.impl.wsdl.WsdlRequest@request-headers">&lt;xml-fragment/></con:setting></con:settings><con:endpoint>http://localhost:8080</con:endpoint><con:request>lalal</con:request><con:originalUri>http://localhost/tomee-hello-world-1.0/helloWorld/withArgument</con:originalUri><con:credentials><con:authType>No Authorization</con:authType></con:credentials><con:jmsConfig JMSDeliveryMode="PERSISTENT"/><con:jmsPropertyConfig/><con:parameters/></con:request></con:method></con:resource><con:method name="HelloWorld 1" id="abd5e99b-325e-4575-85a9-ee992ab3e77f" method="GET"><con:settings/><con:parameters/><con:request name="Request 1" id="7146334b-36cf-4d1a-b31c-91fb1edcb1ca" mediaType="application/json"><con:settings/><con:endpoint>http://localhost:8080</con:endpoint><con:request/><con:credentials><con:authType>No Authorization</con:authType></con:credentials><con:jmsConfig JMSDeliveryMode="PERSISTENT"/><con:jmsPropertyConfig/><con:parameters/></con:request></con:method></con:resource></con:interface><con:properties/><con:wssContainer/><con:oAuth2ProfileContainer/><con:oAuth1ProfileContainer/><con:sensitiveInformation/></con:soapui-project>